flask_errors_as_nested_dicts/__init__.py
flask_errors_as_nested_dicts-0.0.1.dist-info/LICENSE
flask_errors_as_nested_dicts-0.0.1.dist-info/METADATA
flask_errors_as_nested_dicts-0.0.1.dist-info/WHEEL
flask_errors_as_nested_dicts-0.0.1.dist-info/top_level.txt
flask_errors_as_nested_dicts-0.0.1.dist-info/RECORD
